{ "variants": { "facing=east,half=bottom,shape=inner_left": { "model": "bdn:block/stairs/netherrack/inner_stairs", "y": 270, "uvlock": true }, "facing=east,half=bottom,shape=inner_right": { "model": "bdn:block/stairs/netherrack/inner_stairs" }, "facing=east,half=bottom,shape=outer_left": { "model": "bdn:block/stairs/netherrack/outer_stairs", "y": 270, "uvlock": true }, "facing=east,half=bottom,shape=outer_right": { "model": "bdn:block/stairs/netherrack/outer_stairs" }, "facing=east,half=bottom,shape=straight": { "model": "bdn:block/stairs/netherrack/stairs" }, "facing=east,half=top,shape=inner_left": { "model": "bdn:block/stairs/netherrack/inner_stairs", "x": 180, "uvlock": true }, "facing=east,half=top,shape=inner_right": { "model": "bdn:block/stairs/netherrack/inner_stairs", "x": 180, "y": 90, "uvlock": true }, "facing=east,half=top,shape=outer_left": { "model": "bdn:block/stairs/netherrack/outer_stairs", "x": 180, "uvlock": true }, "facing=east,half=top,shape=outer_right": { "model": "bdn:block/stairs/netherrack/outer_stairs", "x": 180, "y": 90, "uvlock": true }, "facing=east,half=top,shape=straight": { "model": "bdn:block/stairs/netherrack/stairs", "x": 180, "uvlock": true }, "facing=north,half=bottom,shape=inner_left": { "model": "bdn:block/stairs/netherrack/inner_stairs", "y": 180, "uvlock": true }, "facing=north,half=bottom,shape=inner_right": { "model": "bdn:block/stairs/netherrack/inner_stairs", "y": 270, "uvlock": true }, "facing=north,half=bottom,shape=outer_left": { "model": "bdn:block/stairs/netherrack/outer_stairs", "y": 180, "uvlock": true }, "facing=north,half=bottom,shape=outer_right": { "model": "bdn:block/stairs/netherrack/outer_stairs", "y": 270, "uvlock": true }, "facing=north,half=bottom,shape=straight": { "model": "bdn:block/stairs/netherrack/stairs", "y": 270, "uvlock": true }, "facing=north,half=top,shape=inner_left": { "model": "bdn:block/stairs/netherrack/inner_stairs", "x": 180, "y": 270, "uvlock": true }, "facing=north,half=top,shape=inner_right": { "model": "bdn:block/stairs/netherrack/inner_stairs", "x": 180, "uvlock": true }, "facing=north,half=top,shape=outer_left": { "model": "bdn:block/stairs/netherrack/outer_stairs", "x": 180, "y": 270, "uvlock": true }, "facing=north,half=top,shape=outer_right": { "model": "bdn:block/stairs/netherrack/outer_stairs", "x": 180, "uvlock": true }, "facing=north,half=top,shape=straight": { "model": "bdn:block/stairs/netherrack/stairs", "x": 180, "y": 270, "uvlock": true }, "facing=south,half=bottom,shape=inner_left": { "model": "bdn:block/stairs/netherrack/inner_stairs" }, "facing=south,half=bottom,shape=inner_right": { "model": "bdn:block/stairs/netherrack/inner_stairs", "y": 90, "uvlock": true }, "facing=south,half=bottom,shape=outer_left": { "model": "bdn:block/stairs/netherrack/outer_stairs" }, "facing=south,half=bottom,shape=outer_right": { "model": "bdn:block/stairs/netherrack/outer_stairs", "y": 90, "uvlock": true }, "facing=south,half=bottom,shape=straight": { "model": "bdn:block/stairs/netherrack/stairs", "y": 90, "uvlock": true }, "facing=south,half=top,shape=inner_left": { "model": "bdn:block/stairs/netherrack/inner_stairs", "x": 180, "y": 90, "uvlock": true }, "facing=south,half=top,shape=inner_right": { "model": "bdn:block/stairs/netherrack/inner_stairs", "x": 180, "y": 180, "uvlock": true }, "facing=south,half=top,shape=outer_left": { "model": "bdn:block/stairs/netherrack/outer_stairs", "x": 180, "y": 90, "uvlock": true }, "facing=south,half=top,shape=outer_right": { "model": "bdn:block/stairs/netherrack/outer_stairs", "x": 180, "y": 180, "uvlock": true }, "facing=south,half=top,shape=straight": { "model": "bdn:block/stairs/netherrack/stairs", "x": 180, "y": 90, "uvlock": true }, "facing=west,half=bottom,shape=inner_left": { "model": "bdn:block/stairs/netherrack/inner_stairs", "y": 90, "uvlock": true }, "facing=west,half=bottom,shape=inner_right": { "model": "bdn:block/stairs/netherrack/inner_stairs", "y": 180, "uvlock": true }, "facing=west,half=bottom,shape=outer_left": { "model": "bdn:block/stairs/netherrack/outer_stairs", "y": 90, "uvlock": true }, "facing=west,half=bottom,shape=outer_right": { "model": "bdn:block/stairs/netherrack/outer_stairs", "y": 180, "uvlock": true }, "facing=west,half=bottom,shape=straight": { "model": "bdn:block/stairs/netherrack/stairs", "y": 180, "uvlock": true }, "facing=west,half=top,shape=inner_left": { "model": "bdn:block/stairs/netherrack/inner_stairs", "x": 180, "y": 180, "uvlock": true }, "facing=west,half=top,shape=inner_right": { "model": "bdn:block/stairs/netherrack/inner_stairs", "x": 180, "y": 270, "uvlock": true }, "facing=west,half=top,shape=outer_left": { "model": "bdn:block/stairs/netherrack/outer_stairs", "x": 180, "y": 180, "uvlock": true }, "facing=west,half=top,shape=outer_right": { "model": "bdn:block/stairs/netherrack/outer_stairs", "x": 180, "y": 270, "uvlock": true }, "facing=west,half=top,shape=straight": { "model": "bdn:block/stairs/netherrack/stairs", "x": 180, "y": 180, "uvlock": true } } }